lago_python_client/__init__.py
lago_python_client/base_client.py
lago_python_client/base_model.py
lago_python_client/client.py
lago_python_client/exceptions.py
lago_python_client/functools_ext.py
lago_python_client/mixins.py
lago_python_client/py.typed
lago_python_client/version.py
lago_python_client/activity_logs/__init__.py
lago_python_client/activity_logs/clients.py
lago_python_client/add_ons/__init__.py
lago_python_client/add_ons/clients.py
lago_python_client/api_logs/__init__.py
lago_python_client/api_logs/clients.py
lago_python_client/billable_metrics/__init__.py
lago_python_client/billable_metrics/clients.py
lago_python_client/billing_entities/__init__.py
lago_python_client/billing_entities/clients.py
lago_python_client/coupons/__init__.py
lago_python_client/coupons/clients.py
lago_python_client/credit_notes/__init__.py
lago_python_client/credit_notes/clients.py
lago_python_client/customers/__init__.py
lago_python_client/customers/applied_coupons_client.py
lago_python_client/customers/clients.py
lago_python_client/customers/credit_notes_client.py
lago_python_client/customers/invoices_client.py
lago_python_client/customers/payment_requests_client.py
lago_python_client/customers/payments_client.py
lago_python_client/customers/subscriptions_client.py
lago_python_client/customers/wallets_client.py
lago_python_client/events/__init__.py
lago_python_client/events/clients.py
lago_python_client/fees/__init__.py
lago_python_client/fees/clients.py
lago_python_client/gross_revenues/__init__.py
lago_python_client/gross_revenues/clients.py
lago_python_client/invoice_collections/__init__.py
lago_python_client/invoice_collections/clients.py
lago_python_client/invoiced_usages/__init__.py
lago_python_client/invoiced_usages/clients.py
lago_python_client/invoices/__init__.py
lago_python_client/invoices/clients.py
lago_python_client/models/__init__.py
lago_python_client/models/activity_log.py
lago_python_client/models/add_on.py
lago_python_client/models/api_log.py
lago_python_client-1.40.0.dist-info/licenses/LICENSE
lago_python_client-1.40.0.dist-info/METADATA
lago_python_client-1.40.0.dist-info/WHEEL
lago_python_client-1.40.0.dist-info/top_level.txt
lago_python_client-1.40.0.dist-info/RECORD
