Metadata-Version: 2.4
Name: lago-python-client
Version: 1.40.0
Summary: Lago Python API Client
Home-page: https://github.com/getlago/lago-python-client
Author: Lovro Colic
Author-email: lovro@getlago.com
Classifier: Development Status :: 4 - Beta
Classifier: Intended Audience :: Developers
Classifier: License :: OSI Approved :: MIT License
Classifier: Operating System :: OS Independent
Classifier: Programming Language :: Python :: 3
Classifier: Programming Language :: Python :: 3 :: Only
Classifier: Programming Language :: Python :: 3.7
Classifier: Programming Language :: Python :: 3.8
Classifier: Programming Language :: Python :: 3.9
Classifier: Programming Language :: Python :: 3.10
Classifier: Programming Language :: Python :: 3.11
Classifier: Topic :: Software Development
Requires-Python: >3.6
License-File: LICENSE
Requires-Dist: classes~=0.4.1
Requires-Dist: httpx<1.0.0,>=0.24.0
Requires-Dist: orjson~=3.8
Requires-Dist: pydantic<3,>=1.10
Requires-Dist: typeguard~=4.0
Provides-Extra: test
Requires-Dist: mypy==0.971; extra == "test"
Requires-Dist: pytest; extra == "test"
Requires-Dist: pytest_httpx; extra == "test"
Provides-Extra: lint
Requires-Dist: ruff; extra == "lint"
Dynamic: license-file
